irods/__init__.py
irods/access.py
irods/account.py
irods/api_number.py
irods/at_client_exit.py
irods/client_init.py
irods/client_server_negotiation.py
irods/collection.py
irods/column.py
irods/connection.py
irods/constants.py
irods/data_object.py
irods/exception.py
irods/genquery2.py
irods/keywords.py
irods/meta.py
irods/models.py
irods/parallel.py
irods/password_obfuscation.py
irods/pool.py
irods/prc_write_irodsA.py
irods/query.py
irods/resource.py
irods/results.py
irods/rule.py
irods/session.py
irods/ticket.py
irods/user.py
irods/version.py
irods/zone.py
irods/auth/__init__.py
irods/auth/native.py
irods/auth/pam.py
irods/auth/pam_interactive.py
irods/auth/pam_password.py
irods/client_configuration/__init__.py
irods/helpers/__init__.py
irods/manager/__init__.py
irods/manager/access_manager.py
irods/manager/collection_manager.py
irods/manager/data_object_manager.py
irods/manager/metadata_manager.py
irods/manager/resource_manager.py
irods/manager/user_manager.py
irods/manager/zone_manager.py
irods/manager/_internal/__init__.py
irods/manager/_internal/_api_impl.py
irods/manager/_internal/_logical_path.py
irods/message/__init__.py
irods/message/message.py
irods/message/ordered.py
irods/message/property_types.py
irods/message/quasixml.py
irods/path/__init__.py
irods/test/README.rst
irods/test/__init__.py
irods/test/access_test.py
irods/test/admin_test.py
irods/test/cleanup_functions_test.py
irods/test/client_hints_test.py
irods/test/collection_test.py
irods/test/connection_test.py
irods/test/data_obj_test.py
irods/test/exception_test.py
irods/test/extended_test.py
irods/test/file_test.py
irods/test/force_create.py
irods/test/genquery2_test.py
irods/test/helpers.py
irods/test/library_features_test.py
irods/test/login_auth_test_must_run_manually.py
irods/test/message_test.py
irods/test/meta_test.py
irods/test/pam_interactive_test.py
irods/test/pool_test.py
irods/test/query_test.py
irods/test/resource_test.py
irods/test/rule_test.py
irods/test/runner.py
python_irodsclient-3.2.0.dist-info/licenses/LICENSE.txt
python_irodsclient-3.2.0.dist-info/METADATA
python_irodsclient-3.2.0.dist-info/WHEEL
python_irodsclient-3.2.0.dist-info/top_level.txt
python_irodsclient-3.2.0.dist-info/RECORD
