Metadata-Version: 2.4
Name: python-irodsclient
Version: 3.2.0
Summary: A python API for iRODS
Home-page: https://github.com/irods/python-irodsclient
Author: iRODS Consortium
Author-email: support@irods.org
License: BSD
Keywords: irods
Classifier: License :: OSI Approved :: BSD License
Classifier: Development Status :: 5 - Production/Stable
Classifier: Programming Language :: Python :: 3.9
Classifier: Programming Language :: Python :: 3.10
Classifier: Programming Language :: Python :: 3.11
Classifier: Programming Language :: Python :: 3.12
Classifier: Programming Language :: Python :: 3.13
Classifier: Operating System :: POSIX :: Linux
License-File: LICENSE.txt
Requires-Dist: PrettyTable>=0.7.2
Requires-Dist: defusedxml
Requires-Dist: jsonpointer
Requires-Dist: jsonpatch
Provides-Extra: tests
Requires-Dist: unittest-xml-reporting; extra == "tests"
Requires-Dist: types-defusedxml; extra == "tests"
Requires-Dist: progressbar; extra == "tests"
Requires-Dist: types-tqdm; extra == "tests"
Dynamic: author
Dynamic: author-email
Dynamic: classifier
Dynamic: description
Dynamic: description-content-type
Dynamic: home-page
Dynamic: keywords
Dynamic: license
Dynamic: license-file
Dynamic: provides-extra
Dynamic: requires-dist
Dynamic: summary
